src/plugin.py
mkdocs_overview_page-1.0.0.dist-info/METADATA
mkdocs_overview_page-1.0.0.dist-info/WHEEL
mkdocs_overview_page-1.0.0.dist-info/entry_points.txt
mkdocs_overview_page-1.0.0.dist-info/RECORD
